mscnltk/__init__.py
mscnltk/cli.py
mscnltk/questions.py
mscnltk-0.1.dist-info/LICENSE
mscnltk-0.1.dist-info/METADATA
mscnltk-0.1.dist-info/WHEEL
mscnltk-0.1.dist-info/entry_points.txt
mscnltk-0.1.dist-info/top_level.txt
mscnltk-0.1.dist-info/RECORD
